morphosource/__about__.py
morphosource/__init__.py
morphosource/config.py
morphosource/download.py
morphosource/exceptions.py
morphosource/fetch.py
morphosource/search.py
morphosource-1.2.0.dist-info/METADATA
morphosource-1.2.0.dist-info/WHEEL
morphosource-1.2.0.dist-info/licenses/LICENSE
morphosource-1.2.0.dist-info/RECORD
