Metadata-Version: 2.1
Name: morphosource
Version: 1.2.0
Summary: Python package for interacting with morphosource.org API
Project-URL: Documentation, https://github.com/Imageomics/pyMorphoSource#readme
Project-URL: Issues, https://github.com/Imageomics/pyMorphoSource/issues
Project-URL: Source, https://github.com/Imageomics/pyMorphoSource
Author-email: John Bradley <johnbradley2008@gmail.com>
License-Expression: MIT
License-File: LICENSE
Classifier: Development Status :: 4 - Beta
Classifier: Programming Language :: Python
Classifier: Programming Language :: Python :: 3.7
Classifier: Programming Language :: Python :: 3.8
Classifier: Programming Language :: Python :: 3.9
Classifier: Programming Language :: Python :: 3.10
Classifier: Programming Language :: Python :: 3.11
Classifier: Programming Language :: Python :: Implementation :: CPython
Classifier: Programming Language :: Python :: Implementation :: PyPy
Requires-Python: >=3.7
Requires-Dist: pygbif
Requires-Dist: requests
